Metadata-Version: 1.0
Name: allurlstatus
Version: 0.1
Summary: pypi package to get status of all urls
Home-page: https://github.com/jogind3r/allurlstatus
Author: jogind3r
Author-email: jogind3r@gmail.com
License: MIT
Keywords: url status
Platform: UNKNOWN
